django_admin_boilerplate/__init__.py
django_admin_boilerplate/admin.py
django_admin_boilerplate/apps.py
django_admin_boilerplate/context_processors.py
django_admin_boilerplate/middleware.py
django_admin_boilerplate/models.py
django_admin_boilerplate/tests.py
django_admin_boilerplate/urls.py
django_admin_boilerplate/views.py
django_admin_boilerplate/__pycache__/__init__.cpython-39.pyc
django_admin_boilerplate/__pycache__/admin.cpython-39.pyc
django_admin_boilerplate/__pycache__/apps.cpython-39.pyc
django_admin_boilerplate/__pycache__/context_processors.cpython-39.pyc
django_admin_boilerplate/__pycache__/models.cpython-39.pyc
django_admin_boilerplate/__pycache__/urls.cpython-39.pyc
django_admin_boilerplate/__pycache__/views.cpython-39.pyc
django_admin_boilerplate/management/__init__.py
django_admin_boilerplate/management/commands/__init__.py
django_admin_boilerplate/management/commands/install_boilerplate.py
django_admin_boilerplate/migrations/0001_initial.py
django_admin_boilerplate/migrations/__init__.py
django_admin_boilerplate/migrations/__pycache__/0001_initial.cpython-39.pyc
django_admin_boilerplate/migrations/__pycache__/__init__.cpython-39.pyc
django_admin_boilerplate/static/admin_boilerplate/css/blue.css
django_admin_boilerplate/static/admin_boilerplate/css/dark.css
django_admin_boilerplate/static/admin_boilerplate/css/default.css
django_admin_boilerplate/static/admin_boilerplate/css/green.css
django_admin_boilerplate/templates/admin_boilerplate/admin_dashboard.html
django_admin_boilerplate/templates/admin_boilerplate/admin_login.html
django_admin_boilerplate/templates/admin_boilerplate/base_admin.html
django_admin_boilerplate/templates/admin_boilerplate/users.html
django_admin_boilerplate-0.1.6.dist-info/LICENSE
django_admin_boilerplate-0.1.6.dist-info/METADATA
django_admin_boilerplate-0.1.6.dist-info/WHEEL
django_admin_boilerplate-0.1.6.dist-info/top_level.txt
django_admin_boilerplate-0.1.6.dist-info/RECORD
