Metadata-Version: 2.2
Name: django_admin_boilerplate
Version: 0.1.6
Summary: A boilerplate for Django admin dashboards
Author-email: Aremu Damilare <a.matthew2013@gmail.com>
License: MIT License
License-File: LICENSE
Requires-Dist: django
